Metadata-Version: 2.1
Name: pulumi-globalgcpcloudrun
Version: 0.0.1a1622189015
Summary: UNKNOWN
Home-page: UNKNOWN
License: UNKNOWN
Platform: UNKNOWN
